{
  "music department": [
    {
      "canonical name": "Chafin, Ashley",
      "name": "Ashley Chafin",
      "long imdb name": "Ashley Chafin",
      "long imdb canonical name": "Chafin, Ashley"
    },
    {
      "canonical name": "Chamberlain, Matt",
      "name": "Matt Chamberlain",
      "long imdb name": "Matt Chamberlain",
      "long imdb canonical name": "Chamberlain, Matt"
    },
    {
      "canonical name": "Culbreath, Wade",
      "name": "Wade Culbreath",
      "long imdb name": "Wade Culbreath",
      "long imdb canonical name": "Culbreath, Wade"
    },
    {
      "canonical name": "Doering, George",
      "name": "George Doering",
      "long imdb name": "George Doering",
      "long imdb canonical name": "Doering, George"
    },
    {
      "canonical name": "Lopez, Robert",
      "name": "Robert Lopez",
      "long imdb name": "Robert Lopez",
      "long imdb canonical name": "Lopez, Robert"
    },
    {
      "canonical name": "Macchia, Frank",
      "name": "Frank Macchia",
      "long imdb name": "Frank Macchia",
      "long imdb canonical name": "Macchia, Frank"
    },
    {
      "canonical name": "Metzger, Dave",
      "name": "Dave Metzger",
      "long imdb name": "Dave Metzger",
      "long imdb canonical name": "Metzger, Dave"
    },
    {
      "canonical name": "Poss, Jason",
      "name": "Jason Poss",
      "long imdb name": "Jason Poss",
      "long imdb canonical name": "Poss, Jason"
    },
    {
      "canonical name": "White, Booker",
      "name": "Booker White",
      "long imdb name": "Booker White",
      "long imdb canonical name": "White, Booker"
    }
  ],
  "distributors": [
    {
      "name": "Falcon",
      "long imdb name": "Falcon"
    },
    {
      "name": "Disney Channel",
      "long imdb name": "Disney Channel"
    },
    {
      "name": "NOS Audiovisuais",
      "long imdb name": "NOS Audiovisuais"
    },
    {
      "name": "Walt Disney Studios Home Entertainment",
      "long imdb name": "Walt Disney Studios Home Entertainment"
    },
    {
      "name": "Walt Disney Studios Motion Pictures",
      "long imdb name": "Walt Disney Studios Motion Pictures"
    }
  ],
  "rating": 7.0,
  "runtimes": [
    "8"
  ],
  "year": 2015,
  "miscellaneous crew": [
    {
      "canonical name": "Amanek, Katie",
      "name": "Katie Amanek",
      "long imdb name": "Katie Amanek",
      "long imdb canonical name": "Amanek, Katie"
    },
    {
      "canonical name": "Fiebiger, Paul",
      "name": "Paul Fiebiger",
      "long imdb name": "Paul Fiebiger",
      "long imdb canonical name": "Fiebiger, Paul"
    },
    {
      "canonical name": "Goldberg, Evan",
      "name": "Evan Goldberg",
      "long imdb name": "Evan Goldberg",
      "long imdb canonical name": "Goldberg, Evan"
    },
    {
      "canonical name": "Henry, Lindsay",
      "name": "Lindsay Henry",
      "long imdb name": "Lindsay Henry",
      "long imdb canonical name": "Henry, Lindsay"
    },
    {
      "canonical name": "Hsu, Belinda M.",
      "name": "Belinda M. Hsu",
      "long imdb name": "Belinda M. Hsu",
      "long imdb canonical name": "Hsu, Belinda M."
    },
    {
      "canonical name": "Manzella, Derek",
      "name": "Derek Manzella",
      "long imdb name": "Derek Manzella",
      "long imdb canonical name": "Manzella, Derek"
    },
    {
      "canonical name": "Scanlan, Elise M.L.",
      "name": "Elise M.L. Scanlan",
      "long imdb name": "Elise M.L. Scanlan",
      "long imdb canonical name": "Scanlan, Elise M.L."
    }
  ],
  "color info": [],
  "visual effects": [
    {
      "canonical name": "Anderson, Michael R.W.",
      "name": "Michael R.W. Anderson",
      "long imdb name": "Michael R.W. Anderson",
      "long imdb canonical name": "Anderson, Michael R.W."
    },
    {
      "canonical name": "Carignan, Chris",
      "name": "Chris Carignan",
      "long imdb name": "Chris Carignan",
      "long imdb canonical name": "Carignan, Chris"
    },
    {
      "canonical name": "Chidanand, Ramya",
      "name": "Ramya Chidanand",
      "long imdb name": "Ramya Chidanand",
      "long imdb canonical name": "Chidanand, Ramya"
    },
    {
      "canonical name": "Culp, Gregory",
      "name": "Gregory Culp",
      "long imdb name": "Gregory Culp",
      "long imdb canonical name": "Culp, Gregory"
    },
    {
      "canonical name": "DeYoung, Ryan",
      "name": "Ryan DeYoung",
      "long imdb name": "Ryan DeYoung",
      "long imdb canonical name": "DeYoung, Ryan"
    },
    {
      "canonical name": "Doi, Kaori",
      "name": "Kaori Doi",
      "long imdb name": "Kaori Doi",
      "long imdb canonical name": "Doi, Kaori"
    },
    {
      "canonical name": "Fulmer, Jack",
      "name": "Jack Fulmer",
      "long imdb name": "Jack Fulmer",
      "long imdb canonical name": "Fulmer, Jack"
    },
    {
      "canonical name": "Ipjian, Katherine",
      "name": "Katherine Ipjian",
      "long imdb name": "Katherine Ipjian",
      "long imdb canonical name": "Ipjian, Katherine"
    },
    {
      "canonical name": "Jacomini, Alessandro",
      "name": "Alessandro Jacomini",
      "long imdb name": "Alessandro Jacomini",
      "long imdb canonical name": "Jacomini, Alessandro"
    },
    {
      "canonical name": "Lee, Roger",
      "name": "Roger Lee",
      "long imdb name": "Roger Lee",
      "long imdb canonical name": "Lee, Roger"
    },
    {
      "canonical name": "Levy, Adam",
      "name": "Adam Levy",
      "long imdb name": "Adam Levy",
      "long imdb canonical name": "Levy, Adam"
    },
    {
      "canonical name": "McBride, Angela",
      "name": "Angela McBride",
      "long imdb name": "Angela McBride",
      "long imdb canonical name": "McBride, Angela"
    },
    {
      "canonical name": "Nabholz, Chris",
      "name": "Chris Nabholz",
      "long imdb name": "Chris Nabholz",
      "long imdb canonical name": "Nabholz, Chris"
    },
    {
      "canonical name": "Narita, Hiroaki",
      "name": "Hiroaki Narita",
      "long imdb name": "Hiroaki Narita",
      "long imdb canonical name": "Narita, Hiroaki"
    },
    {
      "canonical name": "Nelson, Derek",
      "name": "Derek Nelson",
      "long imdb name": "Derek Nelson",
      "long imdb canonical name": "Nelson, Derek"
    },
    {
      "canonical name": "Quitasol, Winston",
      "name": "Winston Quitasol",
      "long imdb name": "Winston Quitasol",
      "long imdb canonical name": "Quitasol, Winston"
    },
    {
      "canonical name": "Raine, Garrett",
      "name": "Garrett Raine",
      "long imdb name": "Garrett Raine",
      "long imdb canonical name": "Raine, Garrett"
    },
    {
      "canonical name": "Castillo, Vanessa Salas",
      "name": "Vanessa Salas Castillo",
      "long imdb name": "Vanessa Salas Castillo",
      "long imdb canonical name": "Castillo, Vanessa Salas"
    },
    {
      "canonical name": "Simpson, Darren",
      "name": "Darren Simpson",
      "long imdb name": "Darren Simpson",
      "long imdb canonical name": "Simpson, Darren"
    },
    {
      "canonical name": "Willy, Elizabeth",
      "name": "Elizabeth Willy",
      "long imdb name": "Elizabeth Willy",
      "long imdb canonical name": "Willy, Elizabeth"
    },
    {
      "canonical name": "Xue, Yezi",
      "name": "Yezi Xue",
      "long imdb name": "Yezi Xue",
      "long imdb canonical name": "Xue, Yezi"
    }
  ],
  "votes": 7804,
  "producer": [
    {
      "canonical name": "Del Vecho, Peter",
      "name": "Peter Del Vecho",
      "long imdb name": "Peter Del Vecho",
      "long imdb canonical name": "Del Vecho, Peter"
    },
    {
      "canonical name": "Lasseter, John",
      "name": "John Lasseter",
      "long imdb name": "John Lasseter",
      "long imdb canonical name": "Lasseter, John"
    },
    {
      "canonical name": "Scribner, Aimee",
      "name": "Aimee Scribner",
      "long imdb name": "Aimee Scribner",
      "long imdb canonical name": "Scribner, Aimee"
    }
  ],
  "title": "Frozen Fever",
  "smart canonical title": "Frozen Fever",
  "writer": [
    {
      "canonical name": "Buck, Chris",
      "name": "Chris Buck",
      "long imdb name": "Chris Buck",
      "long imdb canonical name": "Buck, Chris"
    },
    {
      "canonical name": "Lee, Jennifer",
      "name": "Jennifer Lee",
      "long imdb name": "Jennifer Lee",
      "long imdb canonical name": "Lee, Jennifer"
    },
    {
      "canonical name": "Smith, Marc",
      "name": "Marc Smith",
      "long imdb name": "Marc Smith",
      "long imdb canonical name": "Smith, Marc"
    }
  ],
  "long imdb canonical title": "Frozen Fever (2015)",
  "languages": [
    "English"
  ],
  "production manager": [
    {
      "canonical name": "D'Anna, Angela Frances",
      "name": "Angela Frances D'Anna",
      "long imdb name": "Angela Frances D'Anna",
      "long imdb canonical name": "D'Anna, Angela Frances"
    }
  ],
  "editor": [
    {
      "canonical name": "Draheim, Jeff",
      "name": "Jeff Draheim",
      "long imdb name": "Jeff Draheim",
      "long imdb canonical name": "Draheim, Jeff"
    }
  ],
  "certificates": [
    "Argentina:Atp",
    "Canada:G::(British Columbia)",
    "Hong Kong:I",
    "Japan:G",
    "Mexico:AA",
    "Portugal:M/6",
    "Sweden:Btl",
    "UK:U",
    "USA:G::(certificate #49602)"
  ],
  "sound crew": [
    {
      "canonical name": "Benitez, Odin",
      "name": "Odin Benitez",
      "long imdb name": "Odin Benitez",
      "long imdb canonical name": "Benitez, Odin"
    },
    {
      "canonical name": "Benitez, Odin",
      "name": "Odin Benitez",
      "long imdb name": "Odin Benitez",
      "long imdb canonical name": "Benitez, Odin"
    },
    {
      "canonical name": "Fluhr, David E.",
      "name": "David E. Fluhr",
      "long imdb name": "David E. Fluhr",
      "long imdb canonical name": "Fluhr, David E."
    },
    {
      "canonical name": "Guy, Gabriel",
      "name": "Gabriel Guy",
      "long imdb name": "Gabriel Guy",
      "long imdb canonical name": "Guy, Gabriel"
    },
    {
      "canonical name": "Patel, Darpan",
      "name": "Darpan Patel",
      "long imdb name": "Darpan Patel",
      "long imdb canonical name": "Patel, Darpan"
    },
    {
      "canonical name": "Patel, Darpan",
      "name": "Darpan Patel",
      "long imdb name": "Darpan Patel",
      "long imdb canonical name": "Patel, Darpan"
    },
    {
      "canonical name": "Zebert, Eliza Pollack",
      "name": "Eliza Pollack Zebert",
      "long imdb name": "Eliza Pollack Zebert",
      "long imdb canonical name": "Zebert, Eliza Pollack"
    },
    {
      "canonical name": "Zebert, Eliza Pollack",
      "name": "Eliza Pollack Zebert",
      "long imdb name": "Eliza Pollack Zebert",
      "long imdb canonical name": "Zebert, Eliza Pollack"
    },
    {
      "canonical name": "Salinas, Pernell L.",
      "name": "Pernell L. Salinas",
      "long imdb name": "Pernell L. Salinas",
      "long imdb canonical name": "Salinas, Pernell L."
    },
    {
      "canonical name": "Voss, Brett",
      "name": "Brett Voss",
      "long imdb name": "Brett Voss",
      "long imdb canonical name": "Voss, Brett"
    }
  ],
  "long imdb title": "Frozen Fever (2015)",
  "country codes": [
    "us"
  ],
  "language codes": [
    "en"
  ],
  "cover url": "http://ia.media-imdb.com/images/M/MV5BMTYxMTIxNDEwNV5BMl5BanBnXkFtZTgwODY4ODk1NjE@._V1._SX100_SY133_.jpg",
  "casting department": [
    {
      "canonical name": "Roberts, Jamie Sparer",
      "name": "Jamie Sparer Roberts",
      "long imdb name": "Jamie Sparer Roberts",
      "long imdb canonical name": "Roberts, Jamie Sparer"
    }
  ],
  "editorial department": [
    {
      "canonical name": "Milbourn, Eliot",
      "name": "Eliot Milbourn",
      "long imdb name": "Eliot Milbourn",
      "long imdb canonical name": "Milbourn, Eliot"
    },
    {
      "canonical name": "Millman, Brian",
      "name": "Brian Millman",
      "long imdb name": "Brian Millman",
      "long imdb canonical name": "Millman, Brian"
    },
    {
      "canonical name": "Okey, David",
      "name": "David Okey",
      "long imdb name": "David Okey",
      "long imdb canonical name": "Okey, David"
    },
    {
      "canonical name": "White, Karen A.",
      "name": "Karen A. White",
      "long imdb name": "Karen A. White",
      "long imdb canonical name": "White, Karen A."
    }
  ],
  "genres": [
    "Animation",
    "Short",
    "Adventure",
    "Comedy",
    "Fantasy"
  ],
  "director": [
    {
      "canonical name": "Buck, Chris",
      "name": "Chris Buck",
      "long imdb name": "Chris Buck",
      "long imdb canonical name": "Buck, Chris"
    },
    {
      "canonical name": "Lee, Jennifer",
      "name": "Jennifer Lee",
      "long imdb name": "Jennifer Lee",
      "long imdb canonical name": "Lee, Jennifer"
    }
  ],
  "animation department": [
    {
      "canonical name": "Abril, Alberto",
      "name": "Alberto Abril",
      "long imdb name": "Alberto Abril",
      "long imdb canonical name": "Abril, Alberto"
    },
    {
      "canonical name": "Aguilar, Abraham",
      "name": "Abraham Aguilar",
      "long imdb name": "Abraham Aguilar",
      "long imdb canonical name": "Aguilar, Abraham"
    },
    {
      "canonical name": "Bailey, Kathleen M.",
      "name": "Kathleen M. Bailey",
      "long imdb name": "Kathleen M. Bailey",
      "long imdb canonical name": "Bailey, Kathleen M."
    },
    {
      "canonical name": "Bolwyn, Corey",
      "name": "Corey Bolwyn",
      "long imdb name": "Corey Bolwyn",
      "long imdb canonical name": "Bolwyn, Corey"
    },
    {
      "canonical name": "Bonilla, Tony",
      "name": "Tony Bonilla",
      "long imdb name": "Tony Bonilla",
      "long imdb canonical name": "Bonilla, Tony"
    },
    {
      "canonical name": "Butters, Darrin",
      "name": "Darrin Butters",
      "long imdb name": "Darrin Butters",
      "long imdb canonical name": "Butters, Darrin"
    },
    {
      "canonical name": "Byun, Dong Joo",
      "name": "Dong Joo Byun",
      "long imdb name": "Dong Joo Byun",
      "long imdb canonical name": "Byun, Dong Joo"
    },
    {
      "canonical name": "Choi, Youngjae",
      "name": "Youngjae Choi",
      "long imdb name": "Youngjae Choi",
      "long imdb canonical name": "Choi, Youngjae"
    },
    {
      "canonical name": "Davletshin, Marat",
      "name": "Marat Davletshin",
      "long imdb name": "Marat Davletshin",
      "long imdb canonical name": "Davletshin, Marat"
    },
    {
      "canonical name": "Edwards, Daniel",
      "name": "Daniel Edwards",
      "long imdb name": "Daniel Edwards",
      "long imdb canonical name": "Edwards, Daniel"
    },
    {
      "canonical name": "Franceschi, Michael",
      "name": "Michael Franceschi",
      "long imdb name": "Michael Franceschi",
      "long imdb canonical name": "Franceschi, Michael"
    },
    {
      "canonical name": "Gambell, Jay",
      "name": "Jay Gambell",
      "long imdb name": "Jay Gambell",
      "long imdb canonical name": "Gambell, Jay"
    },
    {
      "canonical name": "Garcia, Jorge",
      "name": "Jorge Garcia",
      "long imdb name": "Jorge Garcia",
      "long imdb canonical name": "Garcia, Jorge"
    },
    {
      "canonical name": "Jennings, Andrew",
      "name": "Andrew Jennings",
      "long imdb name": "Andrew Jennings",
      "long imdb canonical name": "Jennings, Andrew"
    },
    {
      "canonical name": "Joanette, Celeste",
      "name": "Celeste Joanette",
      "long imdb name": "Celeste Joanette",
      "long imdb canonical name": "Joanette, Celeste"
    },
    {
      "canonical name": "Klim, Mike",
      "name": "Mike Klim",
      "long imdb name": "Mike Klim",
      "long imdb canonical name": "Klim, Mike"
    },
    {
      "canonical name": "Kupferer, Tyler",
      "name": "Tyler Kupferer",
      "long imdb name": "Tyler Kupferer",
      "long imdb canonical name": "Kupferer, Tyler"
    },
    {
      "canonical name": "Labrador, Luis",
      "name": "Luis Labrador",
      "long imdb name": "Luis Labrador",
      "long imdb canonical name": "Labrador, Luis"
    },
    {
      "canonical name": "Lane, Ben",
      "name": "Ben Lane",
      "long imdb name": "Ben Lane",
      "long imdb canonical name": "Lane, Ben"
    },
    {
      "canonical name": "Lavertu, Chelsea",
      "name": "Chelsea Lavertu",
      "long imdb name": "Chelsea Lavertu",
      "long imdb canonical name": "Lavertu, Chelsea"
    },
    {
      "canonical name": "Lawson, Andrew",
      "name": "Andrew Lawson",
      "long imdb name": "Andrew Lawson",
      "long imdb canonical name": "Lawson, Andrew"
    },
    {
      "canonical name": "Lee, Kevin",
      "name": "Kevin Lee",
      "long imdb name": "Kevin Lee",
      "long imdb canonical name": "Lee, Kevin"
    },
    {
      "canonical name": "MacLean, Kevin",
      "name": "Kevin MacLean",
      "long imdb name": "Kevin MacLean",
      "long imdb canonical name": "MacLean, Kevin"
    },
    {
      "canonical name": "Megow, Peter",
      "name": "Peter Megow",
      "long imdb name": "Peter Megow",
      "long imdb canonical name": "Megow, Peter"
    },
    {
      "canonical name": "Page, Ryan",
      "name": "Ryan Page",
      "long imdb name": "Ryan Page",
      "long imdb canonical name": "Page, Ryan"
    },
    {
      "canonical name": "Radivoeva, Svetla",
      "name": "Svetla Radivoeva",
      "long imdb name": "Svetla Radivoeva",
      "long imdb canonical name": "Radivoeva, Svetla"
    },
    {
      "canonical name": "Ramjas, Kishan",
      "name": "Kishan Ramjas",
      "long imdb name": "Kishan Ramjas",
      "long imdb canonical name": "Ramjas, Kishan"
    },
    {
      "canonical name": "Robinson, Jason M.",
      "name": "Jason M. Robinson",
      "long imdb name": "Jason M. Robinson",
      "long imdb canonical name": "Robinson, Jason M."
    },
    {
      "canonical name": "Ruiz, Jorge",
      "name": "Jorge Ruiz",
      "long imdb name": "Jorge Ruiz",
      "long imdb canonical name": "Ruiz, Jorge"
    },
    {
      "canonical name": "Slice, Josh",
      "name": "Josh Slice",
      "long imdb name": "Josh Slice",
      "long imdb canonical name": "Slice, Josh"
    },
    {
      "canonical name": "Pierre, Lindsey St.",
      "name": "Lindsey St. Pierre",
      "long imdb name": "Lindsey St. Pierre",
      "long imdb canonical name": "Pierre, Lindsey St."
    },
    {
      "canonical name": "Stellwag, Jason",
      "name": "Jason Stellwag",
      "long imdb name": "Jason Stellwag",
      "long imdb canonical name": "Stellwag, Jason"
    },
    {
      "canonical name": "Stieber, Michael",
      "name": "Michael Stieber",
      "long imdb name": "Michael Stieber",
      "long imdb canonical name": "Stieber, Michael"
    },
    {
      "canonical name": "Talarico, Michael",
      "name": "Michael Talarico",
      "long imdb name": "Michael Talarico",
      "long imdb canonical name": "Talarico, Michael"
    },
    {
      "canonical name": "Ure, Chris",
      "name": "Chris Ure",
      "long imdb name": "Chris Ure",
      "long imdb canonical name": "Ure, Chris"
    },
    {
      "canonical name": "Warr, Gina",
      "name": "Gina Warr",
      "long imdb name": "Gina Warr",
      "long imdb canonical name": "Warr, Gina"
    },
    {
      "canonical name": "Weber, Justin",
      "name": "Justin Weber",
      "long imdb name": "Justin Weber",
      "long imdb canonical name": "Weber, Justin"
    },
    {
      "canonical name": "Wheeler, Geoff",
      "name": "Geoff Wheeler",
      "long imdb name": "Geoff Wheeler",
      "long imdb canonical name": "Wheeler, Geoff"
    },
    {
      "canonical name": "Williams, Jeff",
      "name": "Jeff Williams",
      "long imdb name": "Jeff Williams",
      "long imdb canonical name": "Williams, Jeff"
    },
    {
      "canonical name": "Woodside, Michael",
      "name": "Michael Woodside",
      "long imdb name": "Michael Woodside",
      "long imdb canonical name": "Woodside, Michael"
    }
  ],
  "art direction": [
    {
      "canonical name": "Giaimo, Michael",
      "name": "Michael Giaimo",
      "long imdb name": "Michael Giaimo",
      "long imdb canonical name": "Giaimo, Michael"
    }
  ],
  "akas": [
    "\u013dadov\u00e1 hor\u00fa\u010dka::Slovakia",
    "\u03a7\u03c1\u03cc\u03bd\u03b9\u03b1 \u03c0\u03bf\u03bb\u03bb\u03ac \u03c8\u03c5\u03c7\u03c1\u03ac \u03ba\u03b9 \u03b1\u03bd\u03ac\u03c0\u03bf\u03b4\u03b1::Greece",
    "\u041a\u0440\u0438\u0436\u0430\u043d\u0430 \u043b\u0438\u0445\u043e\u043c\u0430\u043d\u043a\u0430::Ukraine",
    "\u0422\u0440\u0435\u0441\u043a\u0430 \u043f\u043e \u0417\u0430\u043c\u0440\u044a\u0437\u043d\u0430\u043b\u043e\u0442\u043e \u043a\u0440\u0430\u043b\u0441\u0442\u0432\u043e::Bulgaria (Bulgarian title)",
    "\u0425\u043e\u043b\u043e\u0434\u043d\u043e\u0435 \u0442\u043e\u0440\u0436\u0435\u0441\u0442\u0432\u043e::Russia",
    "Ana to Yuki no Joou: Erusa no Sapuraizu::Japan (imdb display title)",
    "Die Eisk\u00f6nigin: Party-Fieber::Germany (imdb display title)",
    "Festa Frozen - O Reino do Gelo::Portugal (imdb display title)",
    "Frostfeber::Norway (imdb display title)",
    "Frostfeber::Sweden (dubbed version)",
    "Frostfeber::Denmark (imdb display title)",
    "Frozen Fiebre Congelada::Mexico (imdb display title)",
    "Frozen-kuumetta::Finland (imdb display title)",
    "Frozen: Febre Congelante::Brazil (imdb display title)",
    "Goraczka lodu::Poland (imdb display title)",
    "J\u00e9gvar\u00e1zs: Party L\u00e1z::Hungary (imdb display title)",
    "Karlar \u00dclkesi: Kutlama::Turkey (Turkish title) (imdb display title)",
    "La Reine des Neiges: Une F\u00eate Givr\u00e9e::France (imdb display title)",
    "Oslava v Ledov\u00e9m kr\u00e1lovstv\u00ed::Czech Republic",
    "Snje\u017ena groznica::Croatia",
    "Talvepalavik::Estonia (imdb display title)",
    "Vro\u010dica Ledenega kraljestva::Slovenia"
  ],
  "aspect ratio": "2.24 : 1",
  "production companies": [
    {
      "name": "Walt Disney Animation Studios",
      "long imdb name": "Walt Disney Animation Studios"
    },
    {
      "name": "Walt Disney Pictures",
      "long imdb name": "Walt Disney Pictures"
    }
  ],
  "kind": "movie",
  "art department": [
    {
      "canonical name": "Keene, Lisa",
      "name": "Lisa Keene",
      "long imdb name": "Lisa Keene",
      "long imdb canonical name": "Keene, Lisa"
    },
    {
      "canonical name": "Reardon, Jim",
      "name": "Jim Reardon",
      "long imdb name": "Jim Reardon",
      "long imdb canonical name": "Reardon, Jim"
    }
  ],
  "countries": [
    "USA"
  ],
  "plot outline": "On Anna's birthday, Elsa and Kristoff are determined to give her the best celebration ever, but Elsa's icy powers may put more than just the party at risk.",
  "plot": [
    "It's Anna's birthday and Elsa plans to throw her the perfect surprise party with the help of Kristoff and Olaf. However, after planning the huge party and as Anna is being led on a \"party treasure hunt,\" Elsa finds that she has caught a cold. She starts sneezing and produces a group of small, cute snow people, much like Olaf, with each sneeze. After some near-misses, a very exhausted Elsa finally makes it with Anna to the courtyard where the party has been arranged. It is a big hit, and at last Anna manages to convince Elsa into letting her to lead her to bed and take care of her. Meanwhile, Olaf has taken the tiny snow creatures under his wing and takes them to Elsa's ice castle with the help of Kristoff.",
    "On Anna's birthday, Elsa and Kristoff are determined to give her the best celebration ever, but Elsa's icy powers may put more than just the party at risk."
  ],
  "full-size cover url": "http://ia.media-imdb.com/images/M/MV5BMTYxMTIxNDEwNV5BMl5BanBnXkFtZTgwODY4ODk1NjE@.jpg",
  "canonical title": "Frozen Fever",
  "cast": [
    {
      "canonical name": "Bell, Kristen",
      "name": "Kristen Bell",
      "long imdb name": "Kristen Bell",
      "long imdb canonical name": "Bell, Kristen"
    },
    {
      "canonical name": "Menzel, Idina",
      "name": "Idina Menzel",
      "long imdb name": "Idina Menzel",
      "long imdb canonical name": "Menzel, Idina"
    },
    {
      "canonical name": "Groff, Jonathan",
      "name": "Jonathan Groff",
      "long imdb name": "Jonathan Groff",
      "long imdb canonical name": "Groff, Jonathan"
    },
    {
      "canonical name": "Gad, Josh",
      "name": "Josh Gad",
      "long imdb name": "Josh Gad",
      "long imdb canonical name": "Gad, Josh"
    },
    {
      "canonical name": "Fontana, Santino",
      "name": "Santino Fontana",
      "long imdb name": "Santino Fontana",
      "long imdb canonical name": "Fontana, Santino"
    },
    {
      "canonical name": "Williams, Chris",
      "name": "Chris Williams",
      "long imdb name": "Chris Williams",
      "long imdb canonical name": "Williams, Chris"
    },
    {
      "canonical name": "Briggs, Paul",
      "name": "Paul Briggs",
      "long imdb name": "Paul Briggs",
      "long imdb canonical name": "Briggs, Paul"
    },
    {
      "canonical name": "Capeless, Grace",
      "name": "Grace Capeless",
      "long imdb name": "Grace Capeless",
      "long imdb canonical name": "Capeless, Grace"
    }
  ],
  "smart long imdb canonical title": "Frozen Fever (2015)",
  "original music": [
    {
      "canonical name": "Beck, Christophe",
      "name": "Christophe Beck",
      "long imdb name": "Christophe Beck",
      "long imdb canonical name": "Beck, Christophe"
    }
  ]
}